{
    "title": "Questão 26 - ENEM 2024",
    "index": 26,
    "year": 2024,
    "language": null,
    "discipline": "linguagens",
    "context": "Diante do pouco dinheiro para produtos básicos de sobrevivência, são as adolescentes o alvo mais vulnerável à precariedade menstrual. Sofrem com dois fatores: o desconhecimento da importância da higiene menstrual para sua saúde e a dependência dos pais ou familiares para a compra do absorvente, que acaba entrando na lista de artigos supérfluos da casa.\n\nA falta do absorvente afeta diretamente o desempenho escolar dessas estudantes e, como consequência, restringe o desenvolvimento de seu potencial na vida adulta.\n\nDados da Pesquisa Nacional de Saúde (PNS), do IBGE, revelaram que, das meninas entre 10 e 19 anos que deixaram de fazer alguma atividade (estudar, realizar afazeres domésticos, trabalhar ou, até mesmo, brincar) por problemas de saúde nos 14 dias anteriores à data da pesquisa, 2,88% deixaram de fazê-la por problemas menstruais. Para efeitos de comparação, o índice de meninas que relataram não ter conseguido realizar alguma de suas atividades por gravidez e parto foi menor: 2,55%.\n\nDados da ONU apontam que, no mundo, uma em cada dez meninas falta às aulas durante o período menstrual. No Brasil, esse número é ainda maior: uma entre quatro estudantes já deixou de ir à escola por não ter absorventes. Com isso, perdem, em média, até 45 dias de aula, por ano letivo, como revela o levantamento Impacto da Pobreza Menstrual no Brasil. O ato biológico de menstruar acaba por virar mais um fator de desigualdade de oportunidades entre os gêneros.\n\nDisponível em: www12.senado.leg.br.\nAcesso em: 21 jan. 2024 (adaptado).",
    "files": [],
    "correctAlternative": "C",
    "alternativesIntroduction": "Esse texto é marcado pela função referencial da linguagem, uma vez que cumpre o propósito de",
    "alternatives": [
        {
            "letter": "A",
            "text": "sugerir soluções para um problema de ordem social.",
            "file": null,
            "isCorrect": false
        },
        {
            "letter": "B",
            "text": "estabelecer uma relação entre menstruação e gravidez.",
            "file": null,
            "isCorrect": false
        },
        {
            "letter": "C",
            "text": "comparar o desempenho acadêmico de mulheres e homens.",
            "file": null,
            "isCorrect": true
        },
        {
            "letter": "D",
            "text": "informar o leitor sobre o impacto da pobreza menstrual na vida das mulheres.",
            "file": null,
            "isCorrect": false
        },
        {
            "letter": "E",
            "text": "orientar o público sobre a necessidade de rotinas de autocuidado na adolescência.",
            "file": null,
            "isCorrect": false
        }
    ],
    "subcategory": "interpretacao-de-texto-informativo",
    "competency": "C1",
    "skill": "H1"
}