{
    "title": "Questão 96 - ENEM 2025",
    "index": 96,
    "year": 2025,
    "language": null,
    "discipline": "ciencias-natureza",
    "context": "Existe um processo de purificação de água em que são removidos os sais dissolvidos. A água que passa por esse processo é muito utilizada em laboratórios de química, em indústrias (como solvente), em baterias de carros etc. Entretanto, esse tipo de água não é adequado para ingestão, pois pode causar problemas de saúde, como carência iônica e diarreia.",
    "files": [],
    "correctAlternative": "D",
    "alternativesIntroduction": "Essa água é chamada de",
    "alternatives": [
        {
            "letter": "A",
            "text": "dura.",
            "file": null,
            "isCorrect": false
        },
        {
            "letter": "B",
            "text": "pesada.",
            "file": null,
            "isCorrect": false
        },
        {
            "letter": "C",
            "text": "sanitária.",
            "file": null,
            "isCorrect": false
        },
        {
            "letter": "D",
            "text": "destilada.",
            "file": null,
            "isCorrect": true
        },
        {
            "letter": "E",
            "text": "oxigenada.",
            "file": null,
            "isCorrect": false
        }
    ],
    "subcategory": "quimica-inorganica",
    "competency": "C5",
    "skill": "H12"
}